uitable/__init__.py
uitable/main.py
uitable/test.py
uitable/utils/__init__.py
uitable/utils/exceptions.py
uitable-0.0.1.dist-info/METADATA
uitable-0.0.1.dist-info/WHEEL
uitable-0.0.1.dist-info/top_level.txt
uitable-0.0.1.dist-info/RECORD
